{"sku":"BK0003","stock":true,"fresh":120,"delivery_day":1,"name":"Bánh Mì gan Panettone Madi Italian Cake (1000g)","image":["https://salt.tikicdn.com/cache/w444/ts/product/c4/46/c3/6e6e7aa9f2a1527a03faddf7dacf24bb.jpg","https://salt.tikicdn.com/cache/w444/ts/product/6a/ea/21/c73fa5981b266468edb0455283796353.jpg","https://vcdn.tikicdn.com/cache/w444/ts/review/9c/d9/15/de7866ea90640fff0554eecaf84e80a1.jpg","https://vcdn.tikicdn.com/cache/w444/ts/review/8d/60/e7/81c60d76893cc5323acffa1b2f9846ea.jpg","https://vcdn.tikicdn.com/cache/w444/ts/review/dc/ab/74/656615bfddb7b199a96aaf5ef9f8555b.jpg"],"price":375000,"currency":"vnđ","short_description":"Hương liệu cao cấp, không chất bản quảnSản xuất theo quy trình công nghệ hiện đạiCó lợi cho sức khỏe người tiêu dùng","main_description":"<div>Hương liệu cao cấp, không chất bản quản<br>Sản xuất theo quy trình công nghệ hiện đại<br>Có lợi cho sức khỏe người tiêu dùng<ul><li><strong>Bánh Mì gan Panettone Madi Italian Cake (1000g) </strong>là loại&nbsp;bánh&nbsp;truyền thống lâu đời.&nbsp;Bánh Madi&nbsp;Ý là sự kết hợp của nghệ thuật nướng&nbsp;bánh&nbsp;cũ với các nguyên liệu: bơ, nho khô, mứt cam quýt và lúa mì theo tiêu chuẩn khắt khe nhất.&nbsp;<br>Mỗi mẻ&nbsp;bánh&nbsp;được làm liên tục 50giờ bằng tay .&nbsp;Bằng tình yêu các thợ&nbsp;bánh&nbsp;Ý đã cho ra&nbsp;bánh Madi&nbsp;giàu dinh dưỡng và đầy hương vị.</li><li>Bánh&nbsp;này ko có bán thường xuyên, người Ý chỉ bán theo đợt. Mỗi năm chỉ có một đợt duy nhất vào dịp Lễ Tạ Ơn.</li><li>Thành phần tự nhiên, an toàn cho người sử dụng.</li><li>Bảo quản: Bảo quản nơi khô ráo thoáng mát. Để giữ bánh luôn tươi mới, mềm mại và đủ độ ẩm, cần giữ bánh trong túi ni lông và cột chặt miếng túi sau khi sử dụng.</li></ul><p>Giá sản phẩm trên Tiki đã bao gồm thuế theo luật hiện hành. Tuy nhiên tuỳ vào từng loại sản phẩm hoặc phương thức, địa chỉ giao hàng mà có thể phát sinh thêm chi phí khác như phí vận chuyển, phụ phí hàng cồng kềnh, ...</p></div>","reviews":[{"comment":"Sản phẩm dùng rất tốt","star":3},{"comment":"Tươi ngon","star":4}],"star":3.5,"faq":[],"store":"5ff2d67a223c8c18c83c4395","brand":"5ff2c65663a9610bd85836ab","category":"5ff2c81e086c7c43b818910f","created_at":1609751021728,"updated_at":1609751021728,"_id":"5ff2d9ed9a064b3c9c2dbdbd"}