{"sku":"F76678148","stock":true,"fresh":120,"delivery_day":1,"name":"Giá Treo Đồ Nhà Tắm 2 tầng INOX 304 lắp đặt Dán Tường tặng kèm đinh vít khoan tường - OENON","image":["https://salt.tikicdn.com/cache/w64/ts/product/53/3e/05/d3d37d19f4f33a12b3d785b361922bf0.jpg","https://salt.tikicdn.com/cache/w64/ts/product/c3/1c/d5/c03764940eab12f6370b761ee806bd40.jpg","https://salt.tikicdn.com/cache/w64/ts/product/3d/7c/c5/ce50cae7fdac40d42027a8b431bc39cf.jpg","https://salt.tikicdn.com/cache/w64/ts/product/b8/14/2e/438acb96d078edd732a1c9e6015876fe.jpg","https://salt.tikicdn.com/cache/w64/ts/product/bc/43/e7/d499b5faea29eb39f8f427ac8176ec83.jpg","https://salt.tikicdn.com/cache/w64/ts/product/fb/98/dc/5596c96e3bb20397767c19759d900e08.jpg"],"specifications":"<tbody><tr><td>Thương hiệu</td><td>OENON</td></tr><tr><td>Xuất xứ thương hiệu</td><td>Trung Quốc</td></tr><tr><td>Dung tích</td><td>2kg</td></tr><tr><td>Model</td><td>2Tang-K304</td></tr><tr><td>Kích thước</td><td>40cm</td></tr><tr><td>Chất liệu</td><td>INOX 304</td></tr><tr><td>Xuất xứ</td><td>Trung Quốc</td></tr><tr><td>Trọng lượng</td><td>2kg</td></tr><tr><td>Tải trọng tối đa</td><td>10kg</td></tr><tr><td>SKU</td><td>7112706665988</td></tr></tbody>","price":289000,"currency":"vnđ","main_description":"<div>Giá treo đồ nhà tắm 2 tầng INOX 304<br>\nNguyên liệu chuẩn Inox  SUS304<br>\nKích thước 40cm  x18cm x 15cm<br>\nLắp đặt Dán Tương - Hoặc Khoan<br>\nTrọng lượng 650gram<br>\nTrọng tải 10kg<br>\nBộ gồm kệ inox 304 + bộ dính tường + bộ vít nở đi kèm<br>\nMàu sắc: Inox sáng bóng như gương<br>\nKệ treo khăn là phụ kiện phòng tắm không thể thiếu được trong mỗi hộ gia đình<br>\nKệ treo khăn 1 tầng inox giúp cho không gian phòng tắm nhà bạn thêm sang trọng.<p><img src=\"https://salt.tikicdn.com/ts/tmp/c3/1c/d5/85762d834b39b7b5dbe2f6e6b19edc6e.jpg\" alt=\"\" width=\"720\" height=\"720\"><img src=\"https://salt.tikicdn.com/ts/tmp/b8/14/2e/c3592b9eb75620209939e51a7fe9f91f.jpg\" alt=\"\" width=\"720\" height=\"720\"><img src=\"https://salt.tikicdn.com/ts/tmp/bc/43/e7/de8cfa1c6d692c70838f8e4e82ffea06.jpg\" alt=\"\" width=\"750\" height=\"750\"></p>\n<p><img src=\"https://salt.tikicdn.com/ts/tmp/fb/98/dc/8aafa8f8901cbaa9064a207560438b9b.jpg\" alt=\"\" width=\"750\" height=\"672\"></p><p>Giá sản phẩm trên Tiki đã bao gồm thuế theo luật hiện hành. Tuy nhiên tuỳ vào từng loại sản phẩm hoặc phương thức, địa chỉ giao hàng mà có thể phát sinh thêm chi phí khác như phí vận chuyển, phụ phí hàng cồng kềnh, ...</p></div><div class=\"gradient\"></div>","reviews":[],"star":5,"faq":[],"store":"5ff2d67a223c8c18c83c4395","brand":"5ff2c65663a9610bd85836ab","category":"5ff2ddc539b8f02c54ef9b23","short_description":"undefined","created_at":1609757924136,"updated_at":1609757924136,"_id":"5ff2f4e4a6e1f841fca7f8d5"}